main.py
manzh/__init__.py
manzh/clean.py
manzh/cli.py
manzh/completion.py
manzh/config.json.example
manzh/config_cli.py
manzh/config_manager.py
manzh/example.py
manzh/list_manuals.py
manzh/man_utils.py
manzh/optimize.py
manzh/translate.py
manzh-1.1.4.data/data/share/man/man1/manzh.1
manzh-1.1.4.dist-info/METADATA
manzh-1.1.4.dist-info/WHEEL
manzh-1.1.4.dist-info/entry_points.txt
manzh-1.1.4.dist-info/top_level.txt
manzh-1.1.4.dist-info/RECORD
