Metadata-Version: 2.4
Name: manzh
Version: 1.1.4
Summary: Man手册中文翻译工具
Home-page: https://github.com/cksdxz1007/ManZH
Author: Cynning Li
Author-email: cynning <me@cynning.uk>
License: MIT
Project-URL: Homepage, https://github.com/cksdxz1007/ManZH
Classifier: Development Status :: 5 - Production/Stable
Classifier: Environment :: Console
Classifier: Intended Audience :: Developers
Classifier: Intended Audience :: System Administrators
Classifier: Operating System :: POSIX :: Linux
Classifier: Operating System :: MacOS :: MacOS X
Classifier: Programming Language :: Python :: 3
Classifier: Programming Language :: Python :: 3.6
Classifier: Programming Language :: Python :: 3.7
Classifier: Programming Language :: Python :: 3.8
Classifier: Programming Language :: Python :: 3.9
Classifier: Programming Language :: Python :: 3.10
Classifier: Topic :: Documentation
Classifier: Topic :: Software Development :: Documentation
Classifier: Topic :: System :: Systems Administration
Classifier: Topic :: Text Processing :: Linguistic
Classifier: Topic :: Utilities
Requires-Python: >=3.6
Requires-Dist: requests>=2.31.0
Requires-Dist: google-generativeai>=0.3.2
Requires-Dist: pytest>=7.4.0
Requires-Dist: pytest-cov>=4.1.0
Requires-Dist: typing-extensions>=4.5.0
Requires-Dist: rich>=13.6.0
Requires-Dist: argcomplete>=1.10.0
Requires-Dist: importlib-metadata>=1.0; python_version < "3.8"
Dynamic: author
Dynamic: home-page
Dynamic: requires-python
